sphinx_breeze_theme/__init__.py
sphinx_breeze_theme/icons.py
sphinx_breeze_theme/links.py
sphinx_breeze_theme/pygments.py
sphinx_breeze_theme/toctree.py
sphinx_breeze_theme/utils.py
sphinx_breeze_theme/assets/fonts/geist/gyByhwUxId8gMEwSGFWfOw.woff2
sphinx_breeze_theme/assets/fonts/geist/gyByhwUxId8gMEwYGFWfOw.woff2
sphinx_breeze_theme/assets/fonts/geist/gyByhwUxId8gMEwcGFU.woff2
sphinx_breeze_theme/assets/fonts/jetbrainsmono/tDbV2o-flEEny0FZhsfKu5WU4xD0OwG_TA.woff2
sphinx_breeze_theme/assets/fonts/jetbrainsmono/tDbV2o-flEEny0FZhsfKu5WU4xD1OwG_TA.woff2
sphinx_breeze_theme/assets/fonts/jetbrainsmono/tDbV2o-flEEny0FZhsfKu5WU4xD2OwG_TA.woff2
sphinx_breeze_theme/assets/fonts/jetbrainsmono/tDbV2o-flEEny0FZhsfKu5WU4xD4OwG_TA.woff2
sphinx_breeze_theme/assets/fonts/jetbrainsmono/tDbV2o-flEEny0FZhsfKu5WU4xD7OwE.woff2
sphinx_breeze_theme/assets/fonts/jetbrainsmono/tDbV2o-flEEny0FZhsfKu5WU4xD_OwG_TA.woff2
sphinx_breeze_theme/assets/fonts/jetbrainsmono/tDbX2o-flEEny0FZhsfKu5WU4xD-Cw2nSHrV.woff2
sphinx_breeze_theme/assets/fonts/jetbrainsmono/tDbX2o-flEEny0FZhsfKu5WU4xD-Cw6nSHrV.woff2
sphinx_breeze_theme/assets/fonts/jetbrainsmono/tDbX2o-flEEny0FZhsfKu5WU4xD-CwCnSHrV.woff2
sphinx_breeze_theme/assets/fonts/jetbrainsmono/tDbX2o-flEEny0FZhsfKu5WU4xD-CwOnSA.woff2
sphinx_breeze_theme/assets/fonts/jetbrainsmono/tDbX2o-flEEny0FZhsfKu5WU4xD-CwenSHrV.woff2
sphinx_breeze_theme/assets/fonts/jetbrainsmono/tDbX2o-flEEny0FZhsfKu5WU4xD-CwynSHrV.woff2
sphinx_breeze_theme/assets/scripts/breeze.ts
sphinx_breeze_theme/assets/scripts/components/back-to-top.ts
sphinx_breeze_theme/assets/scripts/components/dropdown.ts
sphinx_breeze_theme/assets/scripts/components/index.ts
sphinx_breeze_theme/assets/scripts/components/label-button.ts
sphinx_breeze_theme/assets/scripts/components/repo-stats.ts
sphinx_breeze_theme/assets/scripts/components/responsive-tabs.ts
sphinx_breeze_theme/assets/scripts/components/search-button.ts
sphinx_breeze_theme/assets/scripts/components/sidebar-drawer.ts
sphinx_breeze_theme-0.9.0.dist-info/METADATA
sphinx_breeze_theme-0.9.0.dist-info/WHEEL
sphinx_breeze_theme-0.9.0.dist-info/entry_points.txt
sphinx_breeze_theme-0.9.0.dist-info/licenses/LICENSE
sphinx_breeze_theme-0.9.0.dist-info/RECORD
